DeepExperimentManager/__init__.py
DeepExperimentManager/config.py
DeepExperimentManager/datasets.py
DeepExperimentManager/manager.py
DeepExperimentManager/tester.py
DeepExperimentManager/trainer.py
DeepExperimentManager/utils.py
DeepExperimentManager/visualization.py
tests/__init__.py
tests/model.py
tests/preprocessing.py
DeepExperimentManager-1.0.0.dist-info/LICENSE
DeepExperimentManager-1.0.0.dist-info/METADATA
DeepExperimentManager-1.0.0.dist-info/WHEEL
DeepExperimentManager-1.0.0.dist-info/top_level.txt
DeepExperimentManager-1.0.0.dist-info/RECORD
