Metadata-Version: 2.1
Name: DeepExperimentManager
Version: 1.0.0
Summary: A module for training, testing, and managing experiments in PyTorch.
Home-page: https://github.com/Dexoculus/PyTorch-Experiment-Manager
Author: Dexoculus
Author-email: hyeonbin@hanyang.ac.kr
Classifier: Programming Language :: Python :: 3
Classifier: License :: OSI Approved :: MIT License
Classifier: Operating System :: OS Independent
License-File: LICENSE
Requires-Dist: tqdm>=4.64.0
Requires-Dist: pyyaml>=6.0
Requires-Dist: torch>=2.3.1
Requires-Dist: torchvision>=0.15.2
Requires-Dist: numpy>=1.26.4
Requires-Dist: scikit-learn==1.5.1
Requires-Dist: matplotlib>=3.8.0
